activity_monitor/__init__.py
activity_monitor/admin.py
activity_monitor/apps.py
activity_monitor/managers.py
activity_monitor/models.py
activity_monitor/signals.py
activity_monitor/tests.py
activity_monitor/urls.py
activity_monitor/utils.py
activity_monitor/views.py
activity_monitor/fixtures/auth_users.json
activity_monitor/management/__init__.py
activity_monitor/management/commands/__init__.py
activity_monitor/management/commands/register_timeline_content.py
activity_monitor/migrations/0001_initial.py
activity_monitor/migrations/__init__.py
activity_monitor/templates/base.html
activity_monitor/templates/activity_monitor/activity_list.html
activity_monitor/templates/activity_monitor/grouped.html
activity_monitor/templates/activity_monitor/includes/activity_list.html
activity_monitor/templates/activity_monitor/includes/activity_wrapper.html
activity_monitor/templates/activity_monitor/includes/detailed.html
activity_monitor/templates/activity_monitor/includes/grouped_list.html
activity_monitor/templates/activity_monitor/includes/paginate_by_day.html
activity_monitor/templates/activity_monitor/includes/models/forum_post.html
activity_monitor/templates/activity_monitor/includes/models/forum_topic.html
activity_monitor/templatetags/__init__.py
activity_monitor/templatetags/activity_tags.py
activity_monitor-0.13.5.dist-info/METADATA
activity_monitor-0.13.5.dist-info/RECORD
activity_monitor-0.13.5.dist-info/WHEEL
activity_monitor-0.13.5.dist-info/top_level.txt
