Metadata-Version: 2.1
Name: activity-monitor
Version: 0.13.5
Summary: A sort of tumblelog-y thing heavily based on code I got somewhere.
Home-page: http://github.com/tBaxter/activity-monitor
Author: Tim Baxter
Author-email: mail.baxter@gmail.com
License: MIT
Platform: UNKNOWN
